xtagger/__init__.py
xtagger/bert_tagger/__init__.py
xtagger/bert_tagger/bert.py
xtagger/hmm_tagger/__init__.py
xtagger/hmm_tagger/hmm.py
xtagger/hmm_tagger/hmm_utils.py
xtagger/hmm_tagger/viterbi.py
xtagger/lstm_tagger/__init__.py
xtagger/lstm_tagger/lstm.py
xtagger/lstm_tagger/lstm_tagger.py
xtagger/utils/__init__.py
xtagger/utils/data_utils.py
xtagger/utils/metrics.py
xtagger/utils/regex.py
xtagger/utils/tags.py
xtagger/utils/time_utils.py
xtagger/utils/tqdm_config.py
x_tagger-0.1.4.dist-info/LICENSE
x_tagger-0.1.4.dist-info/METADATA
x_tagger-0.1.4.dist-info/WHEEL
x_tagger-0.1.4.dist-info/top_level.txt
x_tagger-0.1.4.dist-info/RECORD
